pysuez/__init__.py
pysuez/__main__.py
pysuez/const.py
pysuez/exception.py
pysuez/models.py
pysuez/py.typed
pysuez/suez_client.py
pysuez/utils.py
pysuezv2-2.0.6.dist-info/METADATA
pysuezv2-2.0.6.dist-info/WHEEL
pysuezv2-2.0.6.dist-info/entry_points.txt
pysuezv2-2.0.6.dist-info/licenses/LICENSE
pysuezv2-2.0.6.dist-info/RECORD
