Metadata-Version: 2.4
Name: pysuezV2
Version: 2.0.6
Summary: Get your water consumption data from your Suez account (www.toutsurmoneau.fr or www.eau-olivet.fr)
Project-URL: Homepage, https://github.com/jb101010-2/pySuez
Project-URL: Issues, https://github.com/jb101010-2/pySuez/issues
Author: Farid N27
Author-email: jb101010-2 <dev.julien.basson@gmail.com>
License-Expression: Apache-2.0
License-File: LICENSE
Keywords: suez,toutsurmoneau,water consumption
Classifier: Operating System :: OS Independent
Classifier: Programming Language :: Python :: 3
Requires-Python: >=3.8
Requires-Dist: aiohttp
